{
    "$schema": "http://json-schema.org/draft-06/schema#",
    "$ref": "#/definitions/Property",
    "definitions": {
        "Property": {
            "type": "object",
            "additionalProperties": false,
            "properties": {
                "name": {
                    "type": "string"
                },
                "type": {
                    "type": "string"
                },
                "value": {
                    "type": [
                        "boolean",
                        "string",
                        "number"
                        ]
                }
            },
            "required": [
                "name",
                "value"
            ],
            "title": "Property"
        }
    }
}